cli_encrypt_txt/__init__.py
cli_encrypt_txt/__main__.py
cli_encrypt_txt-3.2.0.dist-info/licenses/LICENSE.md
cli_encrypt_txt-3.2.0.dist-info/METADATA
cli_encrypt_txt-3.2.0.dist-info/WHEEL
cli_encrypt_txt-3.2.0.dist-info/entry_points.txt
cli_encrypt_txt-3.2.0.dist-info/top_level.txt
cli_encrypt_txt-3.2.0.dist-info/RECORD
