Metadata-Version: 2.4
Name: cli-encrypt-txt
Version: 3.2.0
Summary: Hyper-secure Quantum-Ready CLI file encryptor: AES-256-GCM + Argon2id with opaque steganographic headers
Author-email: Adityakrishna LDK SreeRamachandrarao <adityadronamraju20@gmail.com>
License: MIT
Project-URL: Homepage, https://github.com/sreeramachand/cli-encrypt-txt
Project-URL: Source, https://github.com/sreeramachand/cli-encrypt-txt
Requires-Python: >=3.9
License-File: LICENSE.md
Requires-Dist: cryptography>=42.0.0
Requires-Dist: argon2-cffi>=23.1.0
Dynamic: license-file
